README.md
setup.py
pycalspec/__init__.py
pycalspec/io.py
pycalspec.egg-info/PKG-INFO
pycalspec.egg-info/SOURCES.txt
pycalspec.egg-info/dependency_links.txt
pycalspec.egg-info/top_level.txt
pycalspec/data/calspec_sources.dat