Metadata-Version: 1.1
Name: pycalspec
Version: 0.3.0
Summary: pycalspec: Simple python library to access calspec spectrum 
Home-page: https://github.com/MickaelRigault/pycalspec
Author: Mickael Rigault
Author-email: mrigault@physik.hu-berlin.de
License: Apache 2.0
Download-URL: https://github.com/MickaelRigault/pycalspec/0.2
Platform: UNKNOWN
Classifier: Intended Audience :: Science/Research
Classifier: Programming Language :: Python :: 2.7
Classifier: License :: OSI Approved :: BSD License
Classifier: Topic :: Scientific/Engineering :: Astronomy
Classifier: Operating System :: POSIX
Classifier: Operating System :: Unix
Classifier: Operating System :: MacOS
